route_tts/__init__.py
route_tts/client.py
route_tts/eleven_labs/client.py
route_tts/voices.py
route_tts-0.3.1.dist-info/LICENSE
route_tts-0.3.1.dist-info/METADATA
route_tts-0.3.1.dist-info/WHEEL
route_tts-0.3.1.dist-info/RECORD
