Metadata-Version: 2.1
Name: route-tts
Version: 0.3.1
Summary: A flexible routing library for GenAI text-to-speech (TTS).
Home-page: https://jellypod.ai/route-tts
License: MIT
Author: Pierson Marks
Author-email: pierson@jellypod.ai
Requires-Python: >=3.8,<4.0
Classifier: License :: OSI Approved :: MIT License
Classifier: Programming Language :: Python :: 3
Classifier: Programming Language :: Python :: 3.8
Classifier: Programming Language :: Python :: 3.9
Classifier: Programming Language :: Python :: 3.10
Classifier: Programming Language :: Python :: 3.11
Classifier: Programming Language :: Python :: 3.12
Requires-Dist: elevenlabs (>=1.7.0,<2.0.0)
Requires-Dist: openai (>=1.43.0,<2.0.0)
Requires-Dist: pydantic (>=2.8.2,<3.0.0)
Requires-Dist: pydub (>=0.25.1,<0.26.0)
Requires-Dist: pytest (>=8.3.2,<9.0.0)
Requires-Dist: pytest-asyncio (>=0.24.0,<0.25.0)
